device_detector/__init__.py
device_detector/device_detector.py
device_detector/settings.py
device_detector/utils.py
device_detector/yaml_loader.py
device_detector/appdetails/__init__.py
device_detector/appdetails/antivirus.yml
device_detector/appdetails/app_ids.yml
device_detector/appdetails/desktop_apps.yml
device_detector/appdetails/games.yml
device_detector/appdetails/libraries.yml
device_detector/appdetails/mediaplayers.yml
device_detector/appdetails/messaging.yml
device_detector/appdetails/mobile_apps.yml
device_detector/appdetails/osutility.yml
device_detector/appdetails/p2p.yml
device_detector/appdetails/pim.yml
device_detector/appdetails/vpnproxy.yml
device_detector/appids/__init__.py
device_detector/appids/ignored.yml
device_detector/appids/normalized.yml
device_detector/appids/secondary.yml
device_detector/parser/__init__.py
device_detector/parser/extractors.py
device_detector/parser/key_value_pairs.py
device_detector/parser/operating_system.py
device_detector/parser/os_fragment.py
device_detector/parser/parser.py
device_detector/parser/settings.py
device_detector/parser/client/__init__.py
device_detector/parser/client/base.py
device_detector/parser/client/browser.py
device_detector/parser/client/desktopapp.py
device_detector/parser/client/dictua.py
device_detector/parser/client/extractor_name_version.py
device_detector/parser/client/extractor_whole_name.py
device_detector/parser/client/feed_reader.py
device_detector/parser/client/game.py
device_detector/parser/client/library.py
device_detector/parser/client/mediaplayer.py
device_detector/parser/client/messaging.py
device_detector/parser/client/mobileapp.py
device_detector/parser/client/p2p.py
device_detector/parser/client/pim.py
device_detector/parser/client/vpnproxy.py
device_detector/parser/device/__init__.py
device_detector/parser/device/base.py
device_detector/parser/device/bot.py
device_detector/parser/device/device.py
device_detector/parser/device/vendor_fragment.py
device_detector-0.10.dist-info/METADATA
device_detector-0.10.dist-info/WHEEL
device_detector-0.10.dist-info/top_level.txt
device_detector-0.10.dist-info/zip-safe
device_detector-0.10.dist-info/RECORD
