Metadata-Version: 2.1
Name: device-detector
Version: 0.10
Summary: Python3 port of matomo's Device Detector
Home-page: https://github.com/thinkwelltwd/device_detector
Author: Dave Burkholder
Author-email: dave@thinkwelldesigns.com
License: MIT
Platform: UNKNOWN
Classifier: Environment :: Web Environment
Classifier: Intended Audience :: Developers
Classifier: Operating System :: OS Independent
Classifier: License :: OSI Approved :: MIT License
Classifier: Programming Language :: Python
Classifier: Topic :: Internet :: WWW/HTTP
Classifier: Topic :: Software Development :: Libraries :: Python Modules
Classifier: Programming Language :: Python :: 3.6
Classifier: Programming Language :: Python :: 3.7
Classifier: Programming Language :: Python :: Implementation :: CPython
